{
  "fill" : {
    "linear-gradient" : [
      "display-p3:0.19861,0.19238,0.18164,1.00000",
      "display-p3:0.07959,0.04135,0.00461,1.00000"
    ],
    "orientation" : {
      "start" : {
        "x" : 0.5,
        "y" : 0
      },
      "stop" : {
        "x" : 0.5,
        "y" : 0.7
      }
    }
  },
  "groups" : [
    {
      "layers" : [
        {
          "image-name" : "Group.png",
          "name" : "Group",
          "position" : {
            "scale" : 0.8,
            "translation-in-points" : [
              0,
              0
            ]
          }
        },
        {
          "fill" : "automatic",
          "glass" : false,
          "image-name" : "Group.svg",
          "name" : "Group",
          "opacity" : 0.7,
          "position" : {
            "scale" : 0.8,
            "translation-in-points" : [
              0,
              0
            ]
          }
        }
      ],
      "shadow" : {
        "kind" : "neutral",
        "opacity" : 0.5
      },
      "translucency" : {
        "enabled" : true,
        "value" : 0.5
      }
    }
  ],
  "supported-platforms" : {
    "circles" : [
      "watchOS"
    ],
    "squares" : "shared"
  }
}